{
  "timestamp": "20250821_110050",
  "strategy": "EMA_Only",
  "n_trials": 10,
  "top_count": 1,
  "total_execution_time": 11.84180498123169,
  "selected_coins": [
    {
      "id": "okb",
      "change_24h": 49.66579
    }
  ],
  "results": [
    {
      "crypto_id": "okb",
      "strategy": "EMA_Only",
      "best_value": 111.29087543859228,
      "best_params": {},
      "execution_time": 9.840980529785156,
      "stdout": "\n--- Optimization Finished ---\nNumber of finished trials: 10\nBest trial:\n  Value (Total Profit/Loss): 111.29087543859228\n  Params: \n    short_sma_period: 47\n    long_sma_period: 149\n    short_ema_period: 15\n    long_ema_period: 41\n    rsi_oversold: 29\n    rsi_overbought: 51\n    macd_fast_period: 16\n    macd_slow_period: 34\n    macd_signal_period: 13\n    atr_period: 25\n    atr_multiple: 4.664205711792571\n    fixed_stop_loss_percentage: 0.03010777802647268\n    take_profit_multiple: 1.0143398052497536\n\nBest parameters saved to: best_params_okb_EMA_Only_bayesian.json\n",
      "stderr": "[I 2025-08-21 11:00:39,151] A new study created in memory with name: no-name-17e0c699-370c-4daa-a667-96b4e6642cd1\n[I 2025-08-21 11:00:40,179] Trial 0 finished with value: 111.29087543859228 and parameters: {'short_sma_period': 47, 'long_sma_period': 149, 'short_ema_period': 15, 'long_ema_period': 41, 'rsi_oversold': 29, 'rsi_overbought': 51, 'macd_fast_period': 16, 'macd_slow_period': 34, 'macd_signal_period': 13, 'atr_period': 25, 'atr_multiple': 4.664205711792571, 'fixed_stop_loss_percentage': 0.03010777802647268, 'take_profit_multiple': 1.0143398052497536}. Best is trial 0 with value: 111.29087543859228.\n[I 2025-08-21 11:00:41,108] Trial 1 finished with value: -1000000.0 and parameters: {'short_sma_period': 35, 'long_sma_period': 110, 'short_ema_period': 6, 'long_ema_period': 96, 'rsi_oversold': 17, 'rsi_overbought': 90, 'macd_fast_period': 5, 'macd_slow_period': 28, 'macd_signal_period': 17, 'atr_period': 9, 'atr_multiple': 3.371789617075544, 'fixed_stop_loss_percentage': 0.011988930896545305, 'take_profit_multiple': 2.635203704107923}. Best is trial 0 with value: 111.29087543859228.\n[I 2025-08-21 11:00:42,095] Trial 2 finished with value: -1000000.0 and parameters: {'short_sma_period': 17, 'long_sma_period': 107, 'short_ema_period': 5, 'long_ema_period': 18, 'rsi_oversold': 21, 'rsi_overbought': 83, 'macd_fast_period': 7, 'macd_slow_period': 14, 'macd_signal_period': 13, 'atr_period': 12, 'atr_multiple': 1.0240500035805802, 'fixed_stop_loss_percentage': 0.043669185663453035, 'take_profit_multiple': 4.978834980440515}. Best is trial 0 with value: 111.29087543859228.\n[I 2025-08-21 11:00:42,970] Trial 3 finished with value: -1000000.0 and parameters: {'short_sma_period': 7, 'long_sma_period': 114, 'short_ema_period': 14, 'long_ema_period': 23, 'rsi_oversold': 25, 'rsi_overbought': 54, 'macd_fast_period': 12, 'macd_slow_period': 46, 'macd_signal_period': 11, 'atr_period': 23, 'atr_multiple': 3.7760669140401575, 'fixed_stop_loss_percentage': 0.017388874434581595, 'take_profit_multiple': 4.1909240380417145}. Best is trial 0 with value: 111.29087543859228.\n[I 2025-08-21 11:00:43,804] Trial 4 finished with value: -1000000.0 and parameters: {'short_sma_period': 38, 'long_sma_period': 48, 'short_ema_period': 21, 'long_ema_period': 33, 'rsi_oversold': 21, 'rsi_overbought': 94, 'macd_fast_period': 21, 'macd_slow_period': 40, 'macd_signal_period': 7, 'atr_period': 27, 'atr_multiple': 2.5670758535754086, 'fixed_stop_loss_percentage': 0.04795669943323927, 'take_profit_multiple': 1.458961295522509}. Best is trial 0 with value: 111.29087543859228.\n[I 2025-08-21 11:00:44,799] Trial 5 finished with value: -1000000.0 and parameters: {'short_sma_period': 50, 'long_sma_period': 142, 'short_ema_period': 21, 'long_ema_period': 93, 'rsi_oversold': 28, 'rsi_overbought': 61, 'macd_fast_period': 13, 'macd_slow_period': 25, 'macd_signal_period': 13, 'atr_period': 22, 'atr_multiple': 1.3692068805969835, 'fixed_stop_loss_percentage': 0.016378241484898994, 'take_profit_multiple': 1.5149639134161879}. Best is trial 0 with value: 111.29087543859228.\n[I 2025-08-21 11:00:45,725] Trial 6 finished with value: -1000000.0 and parameters: {'short_sma_period': 12, 'long_sma_period': 20, 'short_ema_period': 30, 'long_ema_period': 68, 'rsi_oversold': 9, 'rsi_overbought': 36, 'macd_fast_period': 25, 'macd_slow_period': 32, 'macd_signal_period': 17, 'atr_period': 19, 'atr_multiple': 1.8230004076401127, 'fixed_stop_loss_percentage': 0.011787937760467958, 'take_profit_multiple': 2.9926577780940287}. Best is trial 0 with value: 111.29087543859228.\n[I 2025-08-21 11:00:46,685] Trial 7 finished with value: -1000000.0 and parameters: {'short_sma_period': 26, 'long_sma_period': 100, 'short_ema_period': 25, 'long_ema_period': 100, 'rsi_oversold': 9, 'rsi_overbought': 79, 'macd_fast_period': 23, 'macd_slow_period': 33, 'macd_signal_period': 13, 'atr_period': 23, 'atr_multiple': 4.874489736773398, 'fixed_stop_loss_percentage': 0.024096448195861618, 'take_profit_multiple': 1.5235596768664839}. Best is trial 0 with value: 111.29087543859228.\n[I 2025-08-21 11:00:47,676] Trial 8 finished with value: -1000000.0 and parameters: {'short_sma_period': 35, 'long_sma_period': 128, 'short_ema_period': 24, 'long_ema_period': 33, 'rsi_oversold': 9, 'rsi_overbought': 92, 'macd_fast_period': 7, 'macd_slow_period': 43, 'macd_signal_period': 6, 'atr_period': 22, 'atr_multiple': 2.650075522344004, 'fixed_stop_loss_percentage': 0.03544281678837233, 'take_profit_multiple': 4.799617877888604}. Best is trial 0 with value: 111.29087543859228.\n[I 2025-08-21 11:00:48,606] Trial 9 finished with value: -1000000.0 and parameters: {'short_sma_period': 30, 'long_sma_period': 71, 'short_ema_period': 8, 'long_ema_period': 100, 'rsi_oversold': 14, 'rsi_overbought': 77, 'macd_fast_period': 17, 'macd_slow_period': 45, 'macd_signal_period': 19, 'atr_period': 7, 'atr_multiple': 1.9576089555249205, 'fixed_stop_loss_percentage': 0.030291730615810683, 'take_profit_multiple': 1.434262686172378}. Best is trial 0 with value: 111.29087543859228.\n"
    }
  ]
}