{
  "crypto_id": "bitcoin",
  "current_price": 113174,
  "latest_data_price": 113890.0,
  "current_signal": "HOLD",
  "strategy_used": "EMA_Only",
  "parameters_used": {
    "short_sma_period": 20,
    "long_sma_period": 50,
    "short_ema_period": 12,
    "long_ema_period": 26,
    "rsi_oversold": 30,
    "rsi_overbought": 70,
    "atr_period": 14,
    "atr_multiple": 2.0,
    "fixed_stop_loss_percentage": 0.01,
    "take_profit_multiple": 1.5,
    "macd_fast_period": 12,
    "macd_slow_period": 26,
    "macd_signal_period": 9,
    "spread_percentage": 0.01,
    "slippage_percentage": 0.001
  },
  "backtest_result": null,
  "active_resistance_lines": [
    {
      "type": "resistance",
      "points": [
        "2025-08-15 12:00:00",
        "2025-08-17 12:00:00"
      ],
      "equation": "y = -0.004317x + 119468.00",
      "slope": -0.00431712962962963,
      "intercept": 119468.0,
      "r_value": -1.0,
      "std_err": 0.0,
      "current_price": 116919.16666666667
    },
    {
      "type": "resistance",
      "points": [
        "2025-08-15 12:00:00",
        "2025-08-18 20:00:00"
      ],
      "equation": "y = -0.009493x + 119915.20",
      "slope": -0.009493055555555555,
      "intercept": 119915.2,
      "r_value": -1.0,
      "std_err": 0.0,
      "current_price": 114310.5
    },
    {
      "type": "resistance",
      "points": [
        "2025-08-17 12:00:00",
        "2025-08-18 20:00:00"
      ],
      "equation": "y = -0.017257x + 122822.00",
      "slope": -0.017256944444444443,
      "intercept": 122822.0,
      "r_value": -1.0,
      "std_err": 0.0,
      "current_price": 112633.5
    }
  ],
  "active_support_lines": [
    {
      "type": "support",
      "points": [
        "2025-08-14 20:00:00",
        "2025-08-15 20:00:00"
      ],
      "equation": "y = -0.014769x + 118674.33",
      "slope": -0.01476851851851852,
      "intercept": 118674.33333333333,
      "r_value": -1.0,
      "std_err": 0.0,
      "current_price": 109955.0
    },
    {
      "type": "support",
      "points": [
        "2025-08-14 20:00:00",
        "2025-08-18 12:00:00"
      ],
      "equation": "y = -0.010294x + 118545.45",
      "slope": -0.010293560606060606,
      "intercept": 118545.45454545454,
      "r_value": -1.0,
      "std_err": 0.0,
      "current_price": 112468.13636363637
    },
    {
      "type": "support",
      "points": [
        "2025-08-14 20:00:00",
        "2025-08-20 00:00:00"
      ],
      "equation": "y = -0.012256x + 118601.97",
      "slope": -0.012255824372759856,
      "intercept": 118601.96774193548,
      "r_value": -1.0,
      "std_err": 0.0,
      "current_price": 111366.12903225806
    },
    {
      "type": "support",
      "points": [
        "2025-08-15 20:00:00",
        "2025-08-18 12:00:00"
      ],
      "equation": "y = -0.008615x + 117965.50",
      "slope": -0.00861545138888889,
      "intercept": 117965.5,
      "r_value": -1.0,
      "std_err": 0.0,
      "current_price": 112878.9375
    },
    {
      "type": "support",
      "points": [
        "2025-08-15 20:00:00",
        "2025-08-20 00:00:00"
      ],
      "equation": "y = -0.011653x + 118315.40",
      "slope": -0.011652777777777778,
      "intercept": 118315.4,
      "r_value": -1.0,
      "std_err": 0.0,
      "current_price": 111435.59999999999
    },
    {
      "type": "support",
      "points": [
        "2025-08-18 12:00:00",
        "2025-08-20 00:00:00"
      ],
      "equation": "y = -0.017052x + 120881.33",
      "slope": -0.01705246913580247,
      "intercept": 120881.33333333333,
      "r_value": -1.0,
      "std_err": 0.0,
      "current_price": 110813.55555555555
    }
  ],
  "next_move_prediction": null,
  "analysis_timestamp": "2025-08-21T14:10:56.871970"
}